ifttt/__init__.py
ifttt/notice.py
ifttt_notice_sdk-1.0.0.dist-info/LICENSE
ifttt_notice_sdk-1.0.0.dist-info/METADATA
ifttt_notice_sdk-1.0.0.dist-info/WHEEL
ifttt_notice_sdk-1.0.0.dist-info/top_level.txt
ifttt_notice_sdk-1.0.0.dist-info/RECORD
