Metadata-Version: 2.1
Name: ifttt-notice-sdk
Version: 1.0.0
Summary: ifttt手机通知发送SDK
Home-page: https://github.com/pypa/sampleproject
Author: 张雷
Author-email: jiayouzl@vip.qq.com
License: Copyright (c) 2018 The Python Packaging Authority        
Platform: UNKNOWN
Classifier: Programming Language :: Python
Classifier: Operating System :: Microsoft :: Windows
Classifier: Operating System :: Unix
Classifier: Programming Language :: Python :: 2.7
Classifier: Programming Language :: Python :: 3.4
Classifier: Programming Language :: Python :: 3.5
Classifier: Programming Language :: Python :: 3.6
Classifier: Programming Language :: Python :: 3.7
Classifier: Programming Language :: Python :: 3.8
Classifier: Programming Language :: Python :: 3.9
Classifier: Programming Language :: Python :: 3.10
License-File: LICENSE
Requires-Dist: requests (>=2.27.1)
